fwadf/__init__.py
fwadf/critical_values.py
fwadf/fwadf.py
fwadf/simulation.py
fwadf/utils.py
fwadf/wadf.py
fwadf/wavelet.py
fwadf-1.0.0.dist-info/licenses/LICENSE
fwadf-1.0.0.dist-info/METADATA
fwadf-1.0.0.dist-info/WHEEL
fwadf-1.0.0.dist-info/top_level.txt
fwadf-1.0.0.dist-info/RECORD
